redocparse/__init__.py
redocparse/files.py
redocparse/logs.py
redocparse/matcher.py
redocparse-0.1.1.dist-info/LICENSE
redocparse-0.1.1.dist-info/METADATA
redocparse-0.1.1.dist-info/WHEEL
redocparse-0.1.1.dist-info/top_level.txt
redocparse-0.1.1.dist-info/RECORD
