Metadata-Version: 2.1
Name: redocparse
Version: 0.1.1
Summary: An ergonomic way to use regex recursively.
Author: lapras
Keywords: docparse,documentation,regex,recursive regex
Requires-Python: >=3.10
License-File: LICENSE
